README.md
setup.cfg
setup.py
gcluster/__init__.py
gcluster/clustering.py
gcluster/graph.py
gcluster.egg-info/PKG-INFO
gcluster.egg-info/SOURCES.txt
gcluster.egg-info/dependency_links.txt
gcluster.egg-info/not-zip-safe
gcluster.egg-info/top_level.txt